UART/UART_Verif/uvc/fifo.sv
module fifo (clk,rst,datain,dataout,rd,wr,emp,full);
input reg clk,rst;
input reg [7:0] datain;
input reg wr,rd;
output reg [7:0] dataout;
output emp,full;
reg [2:0] wr_ptr,rd_ptr;
reg [7:0] memory [7:0]; // the mem is 8X8 deep and wide


assign full = ((wr_ptr == 3'b111) & (rd_ptr == 3'b000) ? 1:0);
assign emp = (rd_ptr == wr_ptr) ? 1:0;

  always @ (posedge clk or posedge rst)
  begin
    if(rst)
	  begin
	    wr_ptr <=0;
	    rd_ptr<=0;
	    //memory[7:0] <= 0;
	  end
	else if(wr & !full)
	  begin
	    memory[wr_ptr] <= datain;
	    wr_ptr <= wr_ptr + 1;
	  end
	else if(rd & !emp)
	  begin
	    dataout <= memory[rd_ptr];
	    rd_ptr <= rd_ptr + 1;
	  end
  end
 
endmodule : fifo

UART/UART_Verif/uvc/tb.sv
`include "fifo.sv"
module tb();
  reg clk,rst;
  reg [7:0] datain;
  reg wr,rd;
  wire [7:0] dataout;
  wire emp,full;
  
  fifo dut(.clk(clk),
	   .rst(rst),
	   .datain(datain),
	   .dataout(dataout),
	   .rd(rd),
	   .wr(wr),
	   .emp(emp),
	   .full(full));
	   
  initial begin
    clk =0;
    rst = 1;
    #10;
    rst =0;
    #10;
    rd=0;wr=1;
    datain= 8'h44;
    #5;
    datain= 8'h55;
    #5;
    datain= 8'h22;
    #5;
    datain= 8'h24;
    #5;
    datain= 8'h77;
    #5;
    datain= 8'h56;
    #5;
    datain= 8'h09;
    #5;
    datain= 8'h45;
    #5;
    
    rd=1;wr=0;
    //if()
    
      $finish;
  end

  always #20 clk = ~ clk;
  
  initial begin
  $dumpvars(0,tb);
  $dumpfile ("res.vcd");
  end

endmodule

UART/UART_Verif/uvc/res.vcd
$date
	Fri Jun 26 19:43:55 2020
$end

$version
	Synopsys VCS version I-2014.03-2
$end

$timescale
	1s
$end

$comment Csum: 1 40f8e4e7d274061d $end


$scope module tb $end
$var reg 1 ! clk $end
$var reg 1 " rst $end
$var reg 8 # datain [7:0] $end
$var reg 1 $ wr $end
$var reg 1 % rd $end
$var wire 8 & dataout [7:0] $end
$var wire 1 ' emp $end
$var wire 1 ( full $end

$scope module dut $end
$var reg 1 ! clk $end
$var reg 1 " rst $end
$var reg 8 # datain [7:0] $end
$var reg 1 $ wr $end
$var reg 1 % rd $end
$var reg 8 ) dataout [7:0] $end
$var wire 1 ' emp $end
$var wire 1 ( full $end
$var reg 3 * wr_ptr [2:0] $end
$var reg 3 + rd_ptr [2:0] $end
$upscope $end

$upscope $end

$enddefinitions $end

#0
$dumpvars
0!
1'
0(
x%
1"
x$
bxxxxxxxx #
bxxxxxxxx )
b000 +
bxxxxxxxx &
b000 *
$end
#10
0"
#20
1!
0%
1$
b01000100 #
b001 *
0'
#25
b01010101 #
#30
b00100010 #
#35
b00100100 #
#40
0!
b01110111 #
#45
b01010110 #
#50
b00001001 #
#55
b01000101 #
#60
1!
1%
0$
